bovine_tool/__init__.py
bovine_tool/cleanup.py
bovine_tool/create.py
bovine_tool/manage.py
bovine_tool/register.py
bovine_tool/store.py
bovine_tool-0.5.6.dist-info/METADATA
bovine_tool-0.5.6.dist-info/WHEEL
bovine_tool-0.5.6.dist-info/RECORD
