Metadata-Version: 2.1
Name: bovine-tool
Version: 0.5.6
Summary: Basic tools to administrate a bovine herd
Home-page: https://codeberg.org/bovine/bovine
Author: Helge
Author-email: helge.krueger@gmail.com
Requires-Python: >=3.11,<4.0
Classifier: Programming Language :: Python :: 3
Classifier: Programming Language :: Python :: 3.11
Requires-Dist: bovine-store (>=0.5.6,<0.6.0)
Project-URL: Repository, https://codeberg.org/bovine/bovine
